defer_imports/__init__.py
defer_imports/py.typed
defer_imports-0.1.1.dist-info/METADATA
defer_imports-0.1.1.dist-info/WHEEL
defer_imports-0.1.1.dist-info/licenses/LICENSE
defer_imports-0.1.1.dist-info/RECORD
