Metadata-Version: 2.3
Name: defer-imports
Version: 0.1.1
Summary: Lazy imports with regular syntax in pure Python.
Project-URL: Homepage, https://github.com/Sachaa-Thanasius/defer-imports
Project-URL: Documentation, https://github.com/Sachaa-Thanasius/defer-imports#readme
Project-URL: Issues, https://github.com/Sachaa-Thanasius/defer-imports/issues
Project-URL: Source, https://github.com/Sachaa-Thanasius/defer-imports
Author-email: Sachaa-Thanasius <sachaathanasius@gmail.com>
License-Expression: MIT
License-File: LICENSE
Classifier: Development Status :: 3 - Alpha
Classifier: Intended Audience :: Developers
Classifier: Natural Language :: English
Classifier: Operating System :: OS Independent
Classifier: Programming Language :: Python :: 3 :: Only
Classifier: Programming Language :: Python :: 3.9
Classifier: Programming Language :: Python :: 3.10
Classifier: Programming Language :: Python :: 3.11
Classifier: Programming Language :: Python :: 3.12
Classifier: Programming Language :: Python :: 3.13
Classifier: Programming Language :: Python :: Implementation :: CPython
Classifier: Programming Language :: Python :: Implementation :: PyPy
Classifier: Topic :: Software Development :: Libraries :: Python Modules
Classifier: Topic :: Utilities
Classifier: Typing :: Typed
Requires-Python: >=3.9
Provides-Extra: bench
Requires-Dist: slothy==1.0.0; extra == 'bench'
Provides-Extra: cov
Requires-Dist: covdefaults; extra == 'cov'
Requires-Dist: coverage; extra == 'cov'
Requires-Dist: pytest; extra == 'cov'
Requires-Dist: pytest-rerunfailures; extra == 'cov'
Provides-Extra: dev
Requires-Dist: covdefaults; extra == 'dev'
Requires-Dist: coverage; extra == 'dev'
Requires-Dist: hatch; extra == 'dev'
Requires-Dist: pre-commit; extra == 'dev'
Requires-Dist: pytest; extra == 'dev'
Requires-Dist: pytest-rerunfailures; extra == 'dev'
Requires-Dist: slothy==1.0.0; extra == 'dev'
Requires-Dist: typing-extensions; extra == 'dev'
Provides-Extra: test
Requires-Dist: pytest; extra == 'test'
Requires-Dist: pytest-rerunfailures; extra == 'test'
